readline.py
pygnurl/__init__.py
pygnurl/bindings.py
pygnurl/callback_mananger.py
pygnurl/errors.py
pygnurl/interface.py
pygnurl/strings.py
pygnurl/typedefs.py
pygnurl/examples/__init__.py
pygnurl/examples/functions.py
pygnurl/examples/mycmd.py
pygnurl/examples/startup.py
pygnurl/modules/__init__.py
pygnurl/modules/readline.py
pygnurl-1.0.1.dist-info/DESCRIPTION.rst
pygnurl-1.0.1.dist-info/METADATA
pygnurl-1.0.1.dist-info/RECORD
pygnurl-1.0.1.dist-info/WHEEL
pygnurl-1.0.1.dist-info/metadata.json
pygnurl-1.0.1.dist-info/top_level.txt
