Metadata-Version: 2.0
Name: pygnurl
Version: 1.0.1
Summary: Dynamic GNU Readline interface
Home-page: https://pypi.python.org/pypi/pygnurl
Author: evanunderscore
Author-email: evanunderscore@gmail.com
License: GNU General Public License v2
Keywords: gnu readline bindings
Platform: UNKNOWN
Classifier: Programming Language :: Python
Classifier: Programming Language :: Python :: 2
Classifier: Programming Language :: Python :: 3
Classifier: License :: OSI Approved :: GNU General Public License v2 (GPLv2)
Classifier: Operating System :: OS Independent
Classifier: Development Status :: 4 - Beta
Classifier: Intended Audience :: Developers
Classifier: Intended Audience :: End Users/Desktop
Requires-Dist: colorama (>=0.3.5); sys_platform=="win32"
